[
  {
    "local_timestamp": "2024-05-31T00:00:01+1000",
    "e_total": 422493.0827777778,
    "e_incremental": 422493.0827777778,
    "e_incremental_watts": 5069916.99333333360020279667,
    "last_energyreal_wac_sum_produced": 339939.0,
    "energyreal_wac_sum_produced": 339939.0,
    "grid_production_incremental": 0,
    "grid_production_incremental_watts": 0,
    "last_energyreal_wac_sum_consumed": 207479.0,
    "energyreal_wac_sum_consumed": 207479.0,
    "grid_consumption_incremental": 0,
    "grid_consumption_incremental_watts": 0,
    "last_internal_consumption_total": 290033.0827777778,
    "internal_consumption_total": 290033.0827777778,
    "internal_consumption_incremental": 0,
    "internal_consumption_incremental_watts": 0,
    "consumption_incremental_watts": 0,
    "p": 0.0,
    "p_grid": 219.31,
    "p_load": -219.31,
    "p_pv": 0.0,
    "rel_autonomy": 0.0,
    "rel_self_consumption": null
  },
  {
    "local_timestamp": "2024-05-31T00:05:00+1000",
    "e_total": 422493.0827777778,
    "e_incremental": 0,
    "e_incremental_watts": 0,
    "last_energyreal_wac_sum_produced": 339939.0,
    "energyreal_wac_sum_produced": 339939.0,
    "grid_production_incremental": 0,
    "grid_production_incremental_watts": 0,
    "last_energyreal_wac_sum_consumed": 207479.0,
    "energyreal_wac_sum_consumed": 207497.0,
    "grid_consumption_incremental": 18.0,
    "grid_consumption_incremental_watts": 216.00000000000000000864,
    "last_internal_consumption_total": 290033.0827777778,
    "internal_consumption_total": 290051.0827777778,
    "internal_consumption_incremental": 18.0000000000,
    "internal_consumption_incremental_watts": 216.00000000000000000864,
    "consumption_incremental_watts": 432.00000000000000001728,
    "p": 0.0,
    "p_grid": 216.80000000000001,
    "p_load": -216.80000000000001,
    "p_pv": 0.0,
    "rel_autonomy": 0.0,
    "rel_self_consumption": null
  },
  {
    "local_timestamp": "2024-05-31T00:10:00+1000",
    "e_total": 422493.0827777778,
    "e_incremental": 0,
    "e_incremental_watts": 0,
    "last_energyreal_wac_sum_produced": 339939.0,
    "energyreal_wac_sum_produced": 339939.0,
    "grid_production_incremental": 0,
    "grid_production_incremental_watts": 0,
    "last_energyreal_wac_sum_consumed": 207497.0,
    "energyreal_wac_sum_consumed": 207516.0,
    "grid_consumption_incremental": 19.0,
    "grid_consumption_incremental_watts": 228.00000000000000000912,
    "last_internal_consumption_total": 290051.0827777778,
    "internal_consumption_total": 290070.0827777778,
    "internal_consumption_incremental": 19.0000000000,
    "internal_consumption_incremental_watts": 228.00000000000000000912,
    "consumption_incremental_watts": 456.00000000000000001824,
    "p": 0.0,
    "p_grid": 219.97999999999999,
    "p_load": -219.97999999999999,
    "p_pv": 0.0,
    "rel_autonomy": 0.0,
    "rel_self_consumption": null
  },
  {
    "local_timestamp": "2024-05-31T00:15:01+1000",
    "e_total": 422493.0827777778,
    "e_incremental": 0,
    "e_incremental_watts": 0,
    "last_energyreal_wac_sum_produced": 339939.0,
    "energyreal_wac_sum_produced": 339939.0,
    "grid_production_incremental": 0,
    "grid_production_incremental_watts": 0,
    "last_energyreal_wac_sum_consumed": 207516.0,
    "energyreal_wac_sum_consumed": 207538.0,
    "grid_consumption_incremental": 22.0,
    "grid_consumption_incremental_watts": 264.00000000000000001056,
    "last_internal_consumption_total": 290070.0827777778,
    "internal_consumption_total": 290092.0827777778,
    "internal_consumption_incremental": 22.0000000000,
    "internal_consumption_incremental_watts": 264.00000000000000001056,
    "consumption_incremental_watts": 528.00000000000000002112,
    "p": 0.0,
    "p_grid": 293.16000000000003,
    "p_load": -293.16000000000003,
    "p_pv": 0.0,
    "rel_autonomy": 0.0,
    "rel_self_consumption": null
  }
]
